{
  "project_info": {
    "project_number": "945201339573",
    "project_id": "workout-tracker-1dc2b",
    "storage_bucket": "workout-tracker-1dc2b.firebasestorage.app"
  },
  "client": [
    {
      "client_info": {
        "mobilesdk_app_id": "1:945201339573:android:8022f45166c6cb2331b2fc",
        "android_client_info": {
          "package_name": "com.example.booklook"
        }
      },
      "oauth_client": [],
      "api_key": [
        {
          "current_key": "AIzaSyAfFusnJT6EkgeCaec_fbtIpzYuyRoW6CU"
        }
      ],
      "services": {
        "appinvite_service": {
          "other_platform_oauth_client": []
        }
      }
    }
  ],
  "configuration_version": "1"
}